odoo/addons/l10n_cl_etd_xerox_fsmroute/README.rst
odoo/addons/l10n_cl_etd_xerox_fsmroute/__init__.py
odoo/addons/l10n_cl_etd_xerox_fsmroute/__manifest__.py
odoo/addons/l10n_cl_etd_xerox_fsmroute/data/etd_document_route_01.xml
odoo/addons/l10n_cl_etd_xerox_fsmroute/data/etd_document_route_05.xml
odoo/addons/l10n_cl_etd_xerox_fsmroute/data/etd_document_route_07.xml
odoo/addons/l10n_cl_etd_xerox_fsmroute/data/etd_document_route_11.xml
odoo/addons/l10n_cl_etd_xerox_fsmroute/i18n/es_CL.po
odoo/addons/l10n_cl_etd_xerox_fsmroute/i18n/l10n_cl_etd_xerox_fsmroute.pot
odoo/addons/l10n_cl_etd_xerox_fsmroute/models/__init__.py
odoo/addons/l10n_cl_etd_xerox_fsmroute/models/etd_document.py
odoo/addons/l10n_cl_etd_xerox_fsmroute/models/etd_mixin.py
odoo/addons/l10n_cl_etd_xerox_fsmroute/models/fsm_route_dayroute.py
odoo/addons/l10n_cl_etd_xerox_fsmroute/readme/CONTRIBUTORS.rst
odoo/addons/l10n_cl_etd_xerox_fsmroute/readme/DESCRIPTION.rst
odoo/addons/l10n_cl_etd_xerox_fsmroute/static/description/icon.png
odoo/addons/l10n_cl_etd_xerox_fsmroute/static/description/index.html
odoo12_addon_l10n_cl_etd_xerox_fsmroute-12.0.1.0.0.99.dev13.dist-info/METADATA
odoo12_addon_l10n_cl_etd_xerox_fsmroute-12.0.1.0.0.99.dev13.dist-info/WHEEL
odoo12_addon_l10n_cl_etd_xerox_fsmroute-12.0.1.0.0.99.dev13.dist-info/top_level.txt
odoo12_addon_l10n_cl_etd_xerox_fsmroute-12.0.1.0.0.99.dev13.dist-info/RECORD
